README.md
pyproject.toml
setup.cfg
setup.py
odm_api/__init__.py
odm_api/api_client.py
odm_api/api_response.py
odm_api/configuration.py
odm_api/exceptions.py
odm_api/py.typed
odm_api/rest.py
odm_api.egg-info/PKG-INFO
odm_api.egg-info/SOURCES.txt
odm_api.egg-info/dependency_links.txt
odm_api.egg-info/requires.txt
odm_api.egg-info/top_level.txt
odm_api/api/__init__.py
odm_api/api/data_import_jobs_api.py
odm_api/api/expression_integration_as_curator_api.py
odm_api/api/expression_integration_as_user_api.py
odm_api/api/expression_spo_tas_curator_api.py
odm_api/api/expression_spo_tas_user_api.py
odm_api/api/files_as_curator_api.py
odm_api/api/files_as_user_api.py
odm_api/api/files_integration_as_curator_api.py
odm_api/api/files_integration_as_user_api.py
odm_api/api/flow_cytometry_facs_integration_as_curator_api.py
odm_api/api/flow_cytometry_facs_integration_as_user_api.py
odm_api/api/flow_cytometry_spo_tas_curator_api.py
odm_api/api/flow_cytometry_spo_tas_user_api.py
odm_api/api/groups_api.py
odm_api/api/job_operations_api.py
odm_api/api/library_integration_as_curator_api.py
odm_api/api/library_integration_as_user_api.py
odm_api/api/library_spo_tas_curator_api.py
odm_api/api/library_spo_tas_user_api.py
odm_api/api/linkage_as_curator_api.py
odm_api/api/linkage_as_user_api.py
odm_api/api/manage_data_api.py
odm_api/api/metadata_versioning_as_curator_api.py
odm_api/api/omics_queries_as_curator_api.py
odm_api/api/omics_queries_as_user_api.py
odm_api/api/preparation_integration_as_curator_api.py
odm_api/api/preparation_integration_as_user_api.py
odm_api/api/preparation_spo_tas_curator_api.py
odm_api/api/preparation_spo_tas_user_api.py
odm_api/api/reference_genome_api.py
odm_api/api/sample_integration_as_curator_api.py
odm_api/api/sample_integration_as_user_api.py
odm_api/api/sample_spo_tas_curator_api.py
odm_api/api/sample_spo_tas_user_api.py
odm_api/api/study_integration_as_curator_api.py
odm_api/api/study_integration_as_user_api.py
odm_api/api/study_spo_tas_curator_api.py
odm_api/api/study_spo_tas_user_api.py
odm_api/api/tasks_api_api.py
odm_api/api/users_api.py
odm_api/api/validation_summary_as_curator_api.py
